git_name/__init__.py
git_name/cli.py
git_name/git_name/__init__.py
git_name/git_name/adjectives.txt
git_name/git_name/adverbs.txt
git_name/git_name/auxiliary_verbs.txt
git_name/git_name/determiners.txt
git_name/git_name/mapper.csv
git_name/git_name/name_generator.py
git_name/git_name/nouns.txt
git_name/git_name/plural_determiners.txt
git_name/git_name/verbs.txt
git_name-0.1.0.dist-info/entry_points.txt
git_name-0.1.0.dist-info/LICENSE
git_name-0.1.0.dist-info/WHEEL
git_name-0.1.0.dist-info/METADATA
git_name-0.1.0.dist-info/RECORD
