Metadata-Version: 2.1
Name: git-name
Version: 0.1.0
Summary: a cli and python package for naming hashes
Home-page: https://github.com/CircArgs/git-name
License: GPL-3.0
Keywords: git,commit,hash,naming
Author: CircArgs
Author-email: quebecname@gmail.com
Requires-Python: >=3.5,<4.0
Classifier: License :: OSI Approved :: GNU General Public License v3 (GPLv3)
Classifier: Programming Language :: Python :: 3
Classifier: Programming Language :: Python :: 3.5
Classifier: Programming Language :: Python :: 3.6
Classifier: Programming Language :: Python :: 3.7
Classifier: Programming Language :: Python :: 3.8
Requires-Dist: inflect (>=4.1.0,<5.0.0)
Project-URL: Repository, https://github.com/CircArgs/git-name
